stock_storage/__init__.py
stock_storage/engine.py
stock_storage/factories.py
stock_storage/main.py
stock_storage/models.py
stock_storage/scheduler.py
stock_storage/collectors/__init__.py
stock_storage/collectors/akshare.py
stock_storage/collectors/base.py
stock_storage/collectors/custom.py
stock_storage/collectors/tushare.py
stock_storage/conditions/__init__.py
stock_storage/conditions/base.py
stock_storage/conditions/custom.py
stock_storage/processors/__init__.py
stock_storage/processors/base.py
stock_storage/processors/custom.py
stock_storage/processors/pandas.py
stock_storage/storages/__init__.py
stock_storage/storages/base.py
stock_storage/storages/csv.py
stock_storage/storages/mysql.py
stock_storage/storages/pgsql.py
stock_storage/storages/sqlite.py
stock_storage_frame-1.0.2.dist-info/licenses/LICENSE
stock_storage_frame-1.0.2.dist-info/METADATA
stock_storage_frame-1.0.2.dist-info/WHEEL
stock_storage_frame-1.0.2.dist-info/entry_points.txt
stock_storage_frame-1.0.2.dist-info/top_level.txt
stock_storage_frame-1.0.2.dist-info/RECORD
