Metadata-Version: 2.4
Name: stock-storage-frame
Version: 1.0.2
Summary: A configuration-driven stock data storage framework
Author-email: Pan Huachao <tzzjchao@126.com>
License: MIT
Project-URL: Homepage, https://gitee.com/panhuachao/stock-storage-frame
Project-URL: Repository, https://gitee.com/panhuachao/stock-storage-frame.git
Classifier: Development Status :: 4 - Beta
Classifier: Intended Audience :: Financial and Insurance Industry
Classifier: License :: OSI Approved :: MIT License
Classifier: Programming Language :: Python :: 3
Classifier: Programming Language :: Python :: 3.8
Classifier: Programming Language :: Python :: 3.9
Classifier: Programming Language :: Python :: 3.10
Classifier: Programming Language :: Python :: 3.11
Classifier: Topic :: Office/Business :: Financial :: Investment
Requires-Python: >=3.8
License-File: LICENSE
Requires-Dist: pandas>=1.5.0
Requires-Dist: numpy>=1.24.0
Requires-Dist: sqlalchemy>=2.0.0
Requires-Dist: pydantic>=2.0.0
Requires-Dist: pyyaml>=6.0
Requires-Dist: loguru>=0.7.0
Requires-Dist: python-dateutil>=2.8.0
Requires-Dist: typing-extensions>=4.5.0
Requires-Dist: croniter>=1.3.0
Requires-Dist: aiomysql>=0.2.0
Requires-Dist: akshare>=1.10.0
Requires-Dist: tushare>=1.2.0
Provides-Extra: dev
Requires-Dist: pytest>=7.0.0; extra == "dev"
Requires-Dist: pytest-cov>=4.0.0; extra == "dev"
Requires-Dist: black>=23.0.0; extra == "dev"
Requires-Dist: isort>=5.12.0; extra == "dev"
Requires-Dist: mypy>=1.0.0; extra == "dev"
Provides-Extra: mysql
Requires-Dist: mysql-connector-python>=8.0.0; extra == "mysql"
Requires-Dist: pymysql>=1.0.0; extra == "mysql"
Requires-Dist: aiomysql>=0.2.0; extra == "mysql"
Provides-Extra: postgresql
Requires-Dist: asyncpg>=0.29.0; extra == "postgresql"
Provides-Extra: akshare
Requires-Dist: akshare>=1.10.0; extra == "akshare"
Provides-Extra: tushare
Requires-Dist: tushare>=1.2.0; extra == "tushare"
Provides-Extra: extra
Requires-Dist: chinese_calendar>=1.11.0; extra == "extra"
Requires-Dist: selenium>=4.0.0; extra == "extra"
Requires-Dist: webdriver-manager>=4.0.0; extra == "extra"
Provides-Extra: all
Requires-Dist: mysql-connector-python>=8.0.0; extra == "all"
Requires-Dist: pymysql>=1.0.0; extra == "all"
Requires-Dist: aiomysql>=0.2.0; extra == "all"
Requires-Dist: psycopg2-binary>=2.9.0; extra == "all"
Requires-Dist: akshare>=1.10.0; extra == "all"
Requires-Dist: tushare>=1.2.0; extra == "all"
Requires-Dist: chinese_calendar>=1.11.0; extra == "all"
Requires-Dist: selenium>=4.0.0; extra == "all"
Requires-Dist: webdriver-manager>=4.0.0; extra == "all"
Dynamic: license-file
